xrheed/__init__.py
xrheed/loaders.py
xrheed/xarray_accessors.py
xrheed/conversion/__init__.py
xrheed/conversion/base.py
xrheed/conversion/image.py
xrheed/kinematics/__init__.py
xrheed/kinematics/cache_utils.py
xrheed/kinematics/ewald.py
xrheed/kinematics/lattice.py
xrheed/plotting/__init__.py
xrheed/plotting/base.py
xrheed/plotting/overview.py
xrheed/plotting/profiles.py
xrheed/plugins/__init__.py
xrheed/plugins/dsnp_arpes_bmp.py
xrheed/plugins/dsnp_arpes_raw.py
xrheed/preparation/__init__.py
xrheed/preparation/alignment.py
xrheed/preparation/filters.py
xrheed-1.3.4.dist-info/licenses/LICENSE
xrheed-1.3.4.dist-info/METADATA
xrheed-1.3.4.dist-info/WHEEL
xrheed-1.3.4.dist-info/top_level.txt
xrheed-1.3.4.dist-info/RECORD
