Metadata-Version: 2.4
Name: xrheed
Version: 1.3.4
Summary: An xarray-based toolkit for RHEED image analysis
Author-email: Marek Kopciuszynski <mkopciuszynski@gmail.com>
License-Expression: MIT
Keywords: RHEED,diffraction,xarray,analysis
Classifier: Programming Language :: Python :: 3
Classifier: Programming Language :: Python :: 3 :: Only
Classifier: Operating System :: OS Independent
Classifier: Topic :: Scientific/Engineering
Classifier: Topic :: Scientific/Engineering :: Physics
Classifier: Intended Audience :: Science/Research
Requires-Python: >=3.12
License-File: LICENSE
Requires-Dist: xarray>=0.18.2
Requires-Dist: numpy>=1.21.0
Requires-Dist: scipy>=1.7.0
Requires-Dist: matplotlib>=3.4.2
Requires-Dist: ruptures>=1.1.7
Requires-Dist: tqdm>=4.62.0
Requires-Dist: lmfit>=1.1.0
Requires-Dist: dill>=0.3.4
Requires-Dist: Pillow>=9.0.0
Provides-Extra: dev
Requires-Dist: ruff; extra == "dev"
Requires-Dist: pytest; extra == "dev"
Requires-Dist: sphinx; extra == "dev"
Requires-Dist: myst-parser; extra == "dev"
Requires-Dist: myst-nb; extra == "dev"
Requires-Dist: nbsphinx; extra == "dev"
Requires-Dist: sphinx-rtd-theme; extra == "dev"
Requires-Dist: build; extra == "dev"
Dynamic: license-file
